[
    {
        "key": "dbln",
        "value": "%7B%2261555739973332%22%3A%22ScyhJSQ7%22%2C%2261559850369147%22%3A%22LrVjrPxw%22%7D",
        "domain": "facebook.com",
        "path": "/login/device-based/",
        "hostOnly": false,
        "creation": "2024-05-23T18:28:16.395Z",
        "lastAccessed": "2024-05-23T18:28:16.395Z"
    },
    {
        "key": "datr",
        "value": "KTCQZT-I-YlZ7l-G31jDxR9E",
        "domain": "facebook.com",
        "path": "/",
        "hostOnly": false,
        "creation": "2024-05-23T18:28:16.395Z",
        "lastAccessed": "2024-05-23T18:28:16.395Z"
    },
    {
        "key": "sb",
        "value": "KTCQZQa3h8HSMpDDvmlyGYZ_",
        "domain": "facebook.com",
        "path": "/",
        "hostOnly": false,
        "creation": "2024-05-23T18:28:16.395Z",
        "lastAccessed": "2024-05-23T18:28:16.395Z"
    },
    {
        "key": "vpd",
        "value": "v1%3B675x360x2",
        "domain": "facebook.com",
        "path": "/",
        "hostOnly": false,
        "creation": "2024-05-23T18:28:16.395Z",
        "lastAccessed": "2024-05-23T18:28:16.395Z"
    },
    {
        "key": "ps_n",
        "value": "1",
        "domain": "facebook.com",
        "path": "/",
        "hostOnly": false,
        "creation": "2024-05-23T18:28:16.395Z",
        "lastAccessed": "2024-05-23T18:28:16.395Z"
    },
    {
        "key": "ps_l",
        "value": "1",
        "domain": "facebook.com",
        "path": "/",
        "hostOnly": false,
        "creation": "2024-05-23T18:28:16.395Z",
        "lastAccessed": "2024-05-23T18:28:16.395Z"
    },
    {
        "key": "m_pixel_ratio",
        "value": "2",
        "domain": "facebook.com",
        "path": "/",
        "hostOnly": false,
        "creation": "2024-05-23T18:28:16.395Z",
        "lastAccessed": "2024-05-23T18:28:16.395Z"
    },
    {
        "key": "wd",
        "value": "360x675",
        "domain": "facebook.com",
        "path": "/",
        "hostOnly": false,
        "creation": "2024-05-23T18:28:16.395Z",
        "lastAccessed": "2024-05-23T18:28:16.395Z"
    },
    {
        "key": "fr",
        "value": "0xFDwoUPcfCHAqah8.AWWpnHZGefgYOyAYMqp8YudjivA.BlkDAp..AAA.0.0.BmT4qo.AWUmrIpQOMA",
        "domain": "facebook.com",
        "path": "/",
        "hostOnly": false,
        "creation": "2024-05-23T18:28:16.395Z",
        "lastAccessed": "2024-05-23T18:28:16.395Z"
    },
    {
        "key": "c_user",
        "value": "61559850369147",
        "domain": "facebook.com",
        "path": "/",
        "hostOnly": false,
        "creation": "2024-05-23T18:28:16.395Z",
        "lastAccessed": "2024-05-23T18:28:16.395Z"
    },
    {
        "key": "xs",
        "value": "44%3Av4wWPK-vUWZ5kg%3A2%3A1716488872%3A-1%3A-1",
        "domain": "facebook.com",
        "path": "/",
        "hostOnly": false,
        "creation": "2024-05-23T18:28:16.395Z",
        "lastAccessed": "2024-05-23T18:28:16.395Z"
    },
    {
        "key": "locale",
        "value": "fr_FR",
        "domain": "facebook.com",
        "path": "/",
        "hostOnly": false,
        "creation": "2024-05-23T18:28:16.395Z",
        "lastAccessed": "2024-05-23T18:28:16.395Z"
    },
    {
        "key": "fbl_st",
        "value": "101020894%3BT%3A28608148",
        "domain": "facebook.com",
        "path": "/",
        "hostOnly": false,
        "creation": "2024-05-23T18:28:16.395Z",
        "lastAccessed": "2024-05-23T18:28:16.395Z"
    },
    {
        "key": "wl_cbv",
        "value": "v2%3Bclient_version%3A2510%3Btimestamp%3A1716488879",
        "domain": "facebook.com",
        "path": "/",
        "hostOnly": false,
        "creation": "2024-05-23T18:28:16.395Z",
        "lastAccessed": "2024-05-23T18:28:16.395Z"
    },
    {
        "key": "m_page_voice",
        "value": "61559850369147",
        "domain": "facebook.com",
        "path": "/",
        "hostOnly": false,
        "creation": "2024-05-23T18:28:16.395Z",
        "lastAccessed": "2024-05-23T18:28:16.395Z"
    }
]
